detectkit/__init__.py
detectkit/alerting/__init__.py
detectkit/alerting/orchestrator.py
detectkit/alerting/channels/__init__.py
detectkit/alerting/channels/base.py
detectkit/alerting/channels/email.py
detectkit/alerting/channels/factory.py
detectkit/alerting/channels/mattermost.py
detectkit/alerting/channels/slack.py
detectkit/alerting/channels/telegram.py
detectkit/alerting/channels/webhook.py
detectkit/cli/__init__.py
detectkit/cli/main.py
detectkit/cli/commands/__init__.py
detectkit/cli/commands/init.py
detectkit/cli/commands/run.py
detectkit/cli/commands/test_alert.py
detectkit/config/__init__.py
detectkit/config/metric_config.py
detectkit/config/profile.py
detectkit/config/project_config.py
detectkit/config/validator.py
detectkit/core/__init__.py
detectkit/core/interval.py
detectkit/core/models.py
detectkit/database/__init__.py
detectkit/database/clickhouse_manager.py
detectkit/database/internal_tables.py
detectkit/database/manager.py
detectkit/database/tables.py
detectkit/detectors/__init__.py
detectkit/detectors/base.py
detectkit/detectors/factory.py
detectkit/detectors/statistical/__init__.py
detectkit/detectors/statistical/iqr.py
detectkit/detectors/statistical/mad.py
detectkit/detectors/statistical/manual_bounds.py
detectkit/detectors/statistical/zscore.py
detectkit/loaders/__init__.py
detectkit/loaders/metric_loader.py
detectkit/loaders/query_template.py
detectkit/orchestration/__init__.py
detectkit/orchestration/task_manager.py
detectkit/utils/__init__.py
detectkit/utils/stats.py
detectkit-0.3.3.dist-info/licenses/LICENSE
detectkit-0.3.3.dist-info/METADATA
detectkit-0.3.3.dist-info/WHEEL
detectkit-0.3.3.dist-info/entry_points.txt
detectkit-0.3.3.dist-info/top_level.txt
detectkit-0.3.3.dist-info/RECORD
