Metadata-Version: 2.4
Name: detectkit
Version: 0.3.3
Summary: Metric monitoring with automatic anomaly detection
Author: detectkit team
License: MIT
Project-URL: Homepage, https://github.com/alexeiveselov92/detectkit
Project-URL: Documentation, https://github.com/alexeiveselov92/detectkit
Project-URL: Repository, https://github.com/alexeiveselov92/detectkit
Project-URL: Issues, https://github.com/alexeiveselov92/detectkit/issues
Keywords: monitoring,anomaly-detection,metrics,timeseries,alerting
Classifier: Development Status :: 3 - Alpha
Classifier: Intended Audience :: Developers
Classifier: Intended Audience :: Science/Research
Classifier: License :: OSI Approved :: MIT License
Classifier: Programming Language :: Python :: 3
Classifier: Programming Language :: Python :: 3.10
Classifier: Programming Language :: Python :: 3.11
Classifier: Programming Language :: Python :: 3.12
Classifier: Topic :: Scientific/Engineering
Classifier: Topic :: System :: Monitoring
Requires-Python: >=3.10
License-File: LICENSE
Requires-Dist: numpy>=1.24.0
Requires-Dist: pydantic>=2.0.0
Requires-Dist: pyyaml>=6.0
Requires-Dist: click>=8.0
Requires-Dist: jinja2>=3.0
Requires-Dist: orjson>=3.0
Requires-Dist: requests>=2.25.0
Provides-Extra: clickhouse
Requires-Dist: clickhouse-driver>=0.2.0; extra == "clickhouse"
Provides-Extra: postgres
Requires-Dist: psycopg2-binary>=2.9.0; extra == "postgres"
Provides-Extra: mysql
Requires-Dist: pymysql>=1.0.0; extra == "mysql"
Provides-Extra: all-db
Requires-Dist: clickhouse-driver>=0.2.0; extra == "all-db"
Requires-Dist: psycopg2-binary>=2.9.0; extra == "all-db"
Requires-Dist: pymysql>=1.0.0; extra == "all-db"
Provides-Extra: prophet
Requires-Dist: prophet>=1.1.0; extra == "prophet"
Provides-Extra: timesfm
Requires-Dist: timesfm>=0.1.0; extra == "timesfm"
Provides-Extra: advanced-detectors
Requires-Dist: prophet>=1.1.0; extra == "advanced-detectors"
Requires-Dist: timesfm>=0.1.0; extra == "advanced-detectors"
Provides-Extra: all
Requires-Dist: clickhouse-driver>=0.2.0; extra == "all"
Requires-Dist: psycopg2-binary>=2.9.0; extra == "all"
Requires-Dist: pymysql>=1.0.0; extra == "all"
Requires-Dist: prophet>=1.1.0; extra == "all"
Requires-Dist: timesfm>=0.1.0; extra == "all"
Provides-Extra: dev
Requires-Dist: pytest>=7.0; extra == "dev"
Requires-Dist: pytest-cov>=4.0; extra == "dev"
Requires-Dist: black>=23.0; extra == "dev"
Requires-Dist: mypy>=1.0; extra == "dev"
Requires-Dist: ruff>=0.1.0; extra == "dev"
Dynamic: license-file
